sandblox/__init__.py
sandblox/core/__init__.py
sandblox/core/block.py
sandblox/core/function.py
sandblox/core/io.py
sandblox/core/stateful.py
sandblox/errors/__init__.py
sandblox/util/__init__.py
sandblox/util/misc.py
sandblox/util/scope.py
sandblox/util/tf_util.py
sandblox-0.1.1.dist-info/METADATA
sandblox-0.1.1.dist-info/RECORD
sandblox-0.1.1.dist-info/WHEEL
sandblox-0.1.1.dist-info/top_level.txt
