Metadata-Version: 2.1
Name: sandblox
Version: 0.1.1
Summary: Declarative programming framework for graph computing libraries
Home-page: https://github.com/SandBlox/sandblox
Author: Reuben John
Author-email: reubenvjohn@gmail.com
License: UNKNOWN
Platform: UNKNOWN
Classifier: Programming Language :: Python :: 3
Classifier: License :: OSI Approved :: MIT License
Classifier: Operating System :: OS Independent
Requires-Dist: tensorflow (<1.11,>=1.8)
Requires-Dist: typing (==3.6.6)
